probabilistic_rule_engine/__init__.py
probabilistic_rule_engine/pre.py
probabilistic_rule_engine-0.1.0.dist-info/WHEEL
probabilistic_rule_engine-0.1.0.dist-info/METADATA
probabilistic_rule_engine-0.1.0.dist-info/RECORD
